README.md
setup.py
TOPSIS_Adit_101803147/__init__.py
TOPSIS_Adit_101803147/topsis.py
TOPSIS_Adit_101803147.egg-info/PKG-INFO
TOPSIS_Adit_101803147.egg-info/SOURCES.txt
TOPSIS_Adit_101803147.egg-info/dependency_links.txt
TOPSIS_Adit_101803147.egg-info/requires.txt
TOPSIS_Adit_101803147.egg-info/top_level.txt