Metadata-Version: 2.1
Name: TOPSIS-Adit-101803147
Version: 0.1
Summary: Topsis Implementation
Home-page: https://github.com/adit6859
Author: Adit Aggarwal
Author-email: adit6859@gmail.com
License: MIT
Download-URL: https://github.com/adit6859/TOPSIS_Adit_101803147/archive/0.1.tar.gz
Keywords: TOPSIS,101803147,Adit Aggarwal
Platform: UNKNOWN
Classifier: Development Status :: 3 - Alpha
Classifier: Intended Audience :: Developers
Classifier: Topic :: Software Development :: Build Tools
Classifier: License :: OSI Approved :: MIT License
Classifier: Programming Language :: Python :: 3
Classifier: Programming Language :: Python :: 3.4
Classifier: Programming Language :: Python :: 3.5
Classifier: Programming Language :: Python :: 3.6
Classifier: Programming Language :: Python :: 3.7
Classifier: Programming Language :: Python :: 3.8
